{ "compressionlevel":-1,
 "editorsettings":
    {
     "export":
        {
         "format":"json",
         "target":"."
        }
    },
 "height":20,
 "infinite":false,
 "layers":[
        {
         "data":[26, 42, 42, 42, 42, 42, 42, 42, 42, 42, 42, 42, 42, 42, 42, 26, 0, 0, 0, 0, 26, 42, 42, 42, 42, 42, 42, 42, 42, 42, 42, 42, 42, 42, 42, 26, 0, 0, 0, 0, 26, 42, 42, 42, 42, 42, 42, 42, 42, 42, 42, 42, 42, 42, 42, 26, 0, 0, 0, 0, 26, 42, 42, 42, 42, 42, 42, 42, 42, 42, 42, 42, 42, 42, 42, 26, 0, 0, 0, 0, 26, 42, 42, 42, 42, 42, 42, 42, 42, 42, 42, 42, 42, 42, 42, 26, 0, 0, 0, 0, 26, 42, 42, 42, 42, 42, 42, 42, 42, 42, 42, 42, 42, 42, 42, 26, 0, 0, 0, 0, 26, 42, 42, 42, 42, 42, 42, 42, 42, 42, 42, 42, 42, 42, 42, 26, 0, 0, 0, 0, 26, 42, 42, 42, 42, 42, 42, 42, 42, 42, 42, 42, 42, 42, 42, 26, 0, 0, 0, 0, 26, 42, 42, 42, 42, 42, 42, 42, 42, 42, 42, 42, 42, 42, 42, 26, 0, 0, 0, 0, 26, 42, 42, 42, 42, 42, 42, 42, 42, 42, 42, 42, 42, 42, 42, 26, 0, 0, 0, 0, 26, 42, 42, 42, 42, 42, 42, 42, 42, 42, 42, 42, 42, 42, 42, 26, 0, 0, 0, 0, 26, 42, 42, 42, 42, 42, 42, 42, 42, 42, 42, 42, 42, 42, 42, 26, 0, 0, 0, 0, 26, 42, 42, 42, 42, 42, 42, 42, 42, 42, 42, 42, 42, 42, 42, 26, 0, 0, 0, 0, 26, 42, 42, 42, 42, 42, 42, 42, 42, 42, 42, 42, 42, 42, 42, 26, 0, 0, 0, 0, 26, 42, 42, 42, 42, 42, 42, 42, 42, 42, 42, 42, 42, 42, 42, 26, 0, 0, 0, 0, 26, 42, 42, 42, 42, 42, 42, 42, 42, 42, 42, 42, 42, 42, 42, 26, 0, 0, 0, 0, 26, 42, 42, 42, 42, 42, 42, 42, 42, 42, 42, 42, 42, 42, 42, 26, 0, 0, 0, 0, 26, 42, 42, 42, 42, 42, 42, 42, 42, 42, 42, 42, 42, 42, 42, 26, 0, 0, 0, 0, 26, 42, 42, 42, 42, 42, 42, 42, 42, 42, 42, 42, 42, 42, 42, 26, 0, 0, 0, 0, 26, 42, 42, 42, 42, 42, 42, 42, 42, 42, 42, 42, 42, 42, 42, 26, 0, 0, 0, 0],
         "height":20,
         "id":1,
         "name":"field",
         "opacity":1,
         "type":"tilelayer",
         "visible":true,
         "width":20,
         "x":0,
         "y":0
        }, 
        {
         "data":[0, 0, 0, 0, 0, 0, 0, 0, 0, 0, 0, 0, 0, 0, 0, 0, 16, 16, 16, 16, 0, 0, 0, 0, 0, 0, 0, 0, 0, 0, 0, 0, 0, 0, 0, 0, 16, 16, 16, 16, 0, 0, 0, 0, 0, 0, 0, 0, 0, 0, 0, 0, 0, 0, 0, 0, 16, 32, 74, 16, 0, 0, 0, 0, 0, 0, 0, 0, 0, 0, 0, 0, 0, 0, 0, 0, 16, 102, 88, 16, 0, 0, 0, 0, 0, 0, 0, 0, 0, 0, 0, 0, 0, 0, 0, 0, 16, 16, 16, 16, 0, 0, 0, 0, 0, 0, 0, 0, 0, 0, 0, 0, 0, 0, 0, 0, 16, 16, 16, 16, 0, 0, 0, 0, 0, 0, 0, 0, 0, 0, 0, 0, 0, 0, 0, 0, 16, 16, 16, 16, 0, 0, 0, 0, 0, 0, 0, 0, 0, 0, 0, 0, 0, 0, 0, 0, 16, 16, 16, 16, 0, 0, 0, 0, 0, 0, 0, 0, 0, 0, 0, 0, 0, 0, 0, 0, 16, 16, 16, 16, 0, 0, 0, 0, 0, 0, 0, 0, 0, 0, 0, 0, 0, 0, 0, 0, 16, 16, 16, 16, 0, 0, 0, 0, 0, 0, 0, 0, 0, 0, 0, 0, 0, 0, 0, 0, 16, 16, 16, 16, 0, 0, 0, 0, 0, 0, 0, 0, 0, 0, 0, 0, 0, 0, 0, 0, 16, 16, 16, 16, 0, 0, 0, 0, 0, 0, 0, 0, 0, 0, 0, 0, 0, 0, 0, 0, 16, 16, 16, 16, 0, 0, 0, 0, 0, 0, 0, 0, 0, 0, 0, 0, 0, 0, 0, 0, 16, 16, 16, 16, 0, 0, 0, 0, 0, 0, 0, 0, 0, 0, 0, 0, 0, 0, 0, 0, 16, 16, 16, 16, 0, 0, 0, 0, 0, 0, 0, 0, 0, 0, 0, 0, 0, 0, 0, 0, 16, 16, 16, 16, 0, 0, 0, 0, 0, 0, 0, 0, 0, 0, 0, 0, 0, 0, 0, 0, 16, 16, 16, 16, 0, 0, 0, 0, 0, 0, 0, 0, 0, 0, 0, 0, 0, 0, 0, 0, 16, 16, 16, 16, 0, 0, 0, 0, 0, 0, 0, 0, 0, 0, 0, 0, 0, 0, 0, 0, 16, 16, 16, 16, 0, 0, 0, 0, 0, 0, 0, 0, 0, 0, 0, 0, 0, 0, 0, 0, 16, 16, 16, 16],
         "height":20,
         "id":7,
         "name":"menu",
         "opacity":1,
         "type":"tilelayer",
         "visible":true,
         "width":20,
         "x":0,
         "y":0
        }, 
        {
         "draworder":"topdown",
         "id":11,
         "name":"gun_1",
         "objects":[
                {
                 "gid":33,
                 "height":32,
                 "id":8,
                 "name":"",
                 "rotation":0,
                 "type":"",
                 "visible":true,
                 "width":32,
                 "x":375.836734693878,
                 "y":219.061224489796
                }],
         "opacity":1,
         "type":"objectgroup",
         "visible":true,
         "x":0,
         "y":0
        }],
 "nextlayerid":12,
 "nextobjectid":9,
 "orientation":"orthogonal",
 "renderorder":"right-down",
 "tiledversion":"2020.10.28",
 "tileheight":32,
 "tilesets":[
        {
         "columns":14,
         "firstgid":1,
         "image":"gridtiles.png",
         "imageheight":320,
         "imagewidth":448,
         "margin":0,
         "name":"tiles",
         "spacing":0,
         "tilecount":140,
         "tileheight":32,
         "tiles":[
                {
                 "id":19,
                 "properties":[
                        {
                         "name":"collide",
                         "type":"bool",
                         "value":true
                        }]
                }, 
                {
                 "id":25,
                 "properties":[
                        {
                         "name":"collide",
                         "type":"bool",
                         "value":false
                        }]
                }, 
                {
                 "id":29,
                 "properties":[
                        {
                         "name":"cost",
                         "type":"int",
                         "value":2
                        }]
                }, 
                {
                 "id":33,
                 "properties":[
                        {
                         "name":"collide",
                         "type":"bool",
                         "value":true
                        }]
                }, 
                {
                 "id":47,
                 "properties":[
                        {
                         "name":"collide",
                         "type":"bool",
                         "value":true
                        }]
                }, 
                {
                 "id":57,
                 "properties":[
                        {
                         "name":"cost",
                         "type":"int",
                         "value":4
                        }]
                }, 
                {
                 "id":61,
                 "properties":[
                        {
                         "name":"collide",
                         "type":"bool",
                         "value":true
                        }]
                }, 
                {
                 "id":71,
                 "properties":[
                        {
                         "name":"cost",
                         "type":"int",
                         "value":3
                        }]
                }, 
                {
                 "id":89,
                 "properties":[
                        {
                         "name":"collide",
                         "type":"bool",
                         "value":true
                        }]
                }, 
                {
                 "id":103,
                 "properties":[
                        {
                         "name":"collide",
                         "type":"bool",
                         "value":true
                        }]
                }, 
                {
                 "id":138,
                 "objectgroup":
                    {
                     "draworder":"index",
                     "id":2,
                     "name":"",
                     "objects":[
                            {
                             "height":32,
                             "id":1,
                             "name":"",
                             "rotation":0,
                             "type":"",
                             "visible":true,
                             "width":32,
                             "x":0,
                             "y":0
                            }, 
                            {
                             "height":32,
                             "id":2,
                             "name":"",
                             "rotation":0,
                             "type":"",
                             "visible":true,
                             "width":32,
                             "x":0,
                             "y":0
                            }],
                     "opacity":1,
                     "type":"objectgroup",
                     "visible":true,
                     "x":0,
                     "y":0
                    }
                }],
         "tilewidth":32
        }],
 "tilewidth":32,
 "type":"map",
 "version":1.4,
 "width":20
}